hamradio/Version.py
hamradio/__init__.py
hamradio/adif.py
hamradio/bandplan.py
hamradio/cty.py
hamradio/dbimport.py
hamradio/dxcc.py
hamradio/eqsl.py
hamradio/lotw.py
hamradio/qslcard.py
hamradio/qth.py
hamradio/requester.py
hamradio/data/2019_Current_Deleted(3).txt
hamradio/data/cty.dat
hamradio/data/wae-country-list.html
hamradio-0.5.dist-info/LICENSE
hamradio-0.5.dist-info/METADATA
hamradio-0.5.dist-info/WHEEL
hamradio-0.5.dist-info/entry_points.txt
hamradio-0.5.dist-info/top_level.txt
hamradio-0.5.dist-info/RECORD
